[
    {
        "author": "github",
        "name": "CopilotForXcode",
        "avatar": "https://github.com/github.png",
        "sponsor": null,
        "url": "https://github.com/github/CopilotForXcode",
        "description": "Xcode extension for GitHub Copilot",
        "language": "Swift",
        "languageColor": "#F05138",
        "stars": 4454,
        "fork": 873,
        "currentPeriodStars": 11,
        "builtBy": [
            {
                "href": "https://github.com/actions-user",
                "avatar": "https://avatars.githubusercontent.com/u/65916846?s=40&v=4",
                "username": "actions-user"
            },
            {
                "href": "https://github.com/devm33",
                "avatar": "https://avatars.githubusercontent.com/u/1682753?s=40&v=4",
                "username": "devm33"
            },
            {
                "href": "https://github.com/eliperkins",
                "avatar": "https://avatars.githubusercontent.com/u/1051453?s=40&v=4",
                "username": "eliperkins"
            },
            {
                "href": "https://github.com/justb0b",
                "avatar": "https://avatars.githubusercontent.com/u/144845785?s=40&v=4",
                "username": "justb0b"
            }
        ]
    },
    {
        "author": "nikitabobko",
        "name": "AeroSpace",
        "avatar": "https://github.com/nikitabobko.png",
        "sponsor": "https://github.com/sponsors/nikitabobko",
        "url": "https://github.com/nikitabobko/AeroSpace",
        "description": "AeroSpace is an i3-like tiling window manager for macOS",
        "language": "Swift",
        "languageColor": "#F05138",
        "stars": 14157,
        "fork": 282,
        "currentPeriodStars": 45,
        "builtBy": [
            {
                "href": "https://github.com/nikitabobko",
                "avatar": "https://avatars.githubusercontent.com/u/20517828?s=40&v=4",
                "username": "nikitabobko"
            },
            {
                "href": "https://github.com/mobile-ar",
                "avatar": "https://avatars.githubusercontent.com/u/758096?s=40&v=4",
                "username": "mobile-ar"
            },
            {
                "href": "https://github.com/jakenvac",
                "avatar": "https://avatars.githubusercontent.com/u/9119973?s=40&v=4",
                "username": "jakenvac"
            },
            {
                "href": "https://github.com/rickyz",
                "avatar": "https://avatars.githubusercontent.com/u/616784?s=40&v=4",
                "username": "rickyz"
            },
            {
                "href": "https://github.com/Henkru",
                "avatar": "https://avatars.githubusercontent.com/u/4019880?s=40&v=4",
                "username": "Henkru"
            }
        ]
    },
    {
        "author": "apple",
        "name": "swift-nio",
        "avatar": "https://github.com/apple.png",
        "sponsor": null,
        "url": "https://github.com/apple/swift-nio",
        "description": "Event-driven network application framework for high performance protocol servers & clients, non-blocking.",
        "language": "Swift",
        "languageColor": "#F05138",
        "stars": 8206,
        "fork": 691,
        "currentPeriodStars": 3,
        "builtBy": [
            {
                "href": "https://github.com/weissi",
                "avatar": "https://avatars.githubusercontent.com/u/624238?s=40&v=4",
                "username": "weissi"
            },
            {
                "href": "https://github.com/Lukasa",
                "avatar": "https://avatars.githubusercontent.com/u/1382556?s=40&v=4",
                "username": "Lukasa"
            },
            {
                "href": "https://github.com/normanmaurer",
                "avatar": "https://avatars.githubusercontent.com/u/439362?s=40&v=4",
                "username": "normanmaurer"
            },
            {
                "href": "https://github.com/glbrntt",
                "avatar": "https://avatars.githubusercontent.com/u/5047671?s=40&v=4",
                "username": "glbrntt"
            },
            {
                "href": "https://github.com/FranzBusch",
                "avatar": "https://avatars.githubusercontent.com/u/3491887?s=40&v=4",
                "username": "FranzBusch"
            }
        ]
    },
    {
        "author": "RevenueCat",
        "name": "purchases-ios",
        "avatar": "https://github.com/RevenueCat.png",
        "sponsor": null,
        "url": "https://github.com/RevenueCat/purchases-ios",
        "description": "In-app purchases and subscriptions made easy. Support for iOS, watchOS, tvOS, macOS, and visionOS.",
        "language": "Swift",
        "languageColor": "#F05138",
        "stars": 2721,
        "fork": 372,
        "currentPeriodStars": 3,
        "builtBy": [
            {
                "href": "https://github.com/NachoSoto",
                "avatar": "https://avatars.githubusercontent.com/u/685609?s=40&v=4",
                "username": "NachoSoto"
            },
            {
                "href": "https://github.com/aboedo",
                "avatar": "https://avatars.githubusercontent.com/u/3922667?s=40&v=4",
                "username": "aboedo"
            },
            {
                "href": "https://github.com/jeiting",
                "avatar": "https://avatars.githubusercontent.com/u/138742?s=40&v=4",
                "username": "jeiting"
            },
            {
                "href": "https://github.com/vegaro",
                "avatar": "https://avatars.githubusercontent.com/u/664544?s=40&v=4",
                "username": "vegaro"
            },
            {
                "href": "https://github.com/RCGitBot",
                "avatar": "https://avatars.githubusercontent.com/u/72824662?s=40&v=4",
                "username": "RCGitBot"
            }
        ]
    },
    {
        "author": "Whisky-App",
        "name": "Whisky",
        "avatar": "https://github.com/Whisky-App.png",
        "sponsor": null,
        "url": "https://github.com/Whisky-App/Whisky",
        "description": "A modern Wine wrapper for macOS built with SwiftUI",
        "language": "Swift",
        "languageColor": "#F05138",
        "stars": 14634,
        "fork": 410,
        "currentPeriodStars": 1,
        "builtBy": [
            {
                "href": "https://github.com/IsaacMarovitz",
                "avatar": "https://avatars.githubusercontent.com/u/42140194?s=40&v=4",
                "username": "IsaacMarovitz"
            },
            {
                "href": "https://github.com/ohaiibuzzle",
                "avatar": "https://avatars.githubusercontent.com/u/23693150?s=40&v=4",
                "username": "ohaiibuzzle"
            },
            {
                "href": "https://github.com/Mika412",
                "avatar": "https://avatars.githubusercontent.com/u/5073663?s=40&v=4",
                "username": "Mika412"
            },
            {
                "href": "https://github.com/cuba",
                "avatar": "https://avatars.githubusercontent.com/u/909331?s=40&v=4",
                "username": "cuba"
            },
            {
                "href": "https://github.com/alexsch01",
                "avatar": "https://avatars.githubusercontent.com/u/5721147?s=40&v=4",
                "username": "alexsch01"
            }
        ]
    },
    {
        "author": "altstoreio",
        "name": "AltStore",
        "avatar": "https://github.com/altstoreio.png",
        "sponsor": null,
        "url": "https://github.com/altstoreio/AltStore",
        "description": "AltStore is an alternative app store for non-jailbroken iOS devices.",
        "language": "Swift",
        "languageColor": "#F05138",
        "stars": 12674,
        "fork": 1080,
        "currentPeriodStars": 7,
        "builtBy": [
            {
                "href": "https://github.com/rileytestut",
                "avatar": "https://avatars.githubusercontent.com/u/705880?s=40&v=4",
                "username": "rileytestut"
            },
            {
                "href": "https://github.com/shanegillio",
                "avatar": "https://avatars.githubusercontent.com/u/99302292?s=40&v=4",
                "username": "shanegillio"
            },
            {
                "href": "https://github.com/tbodt",
                "avatar": "https://avatars.githubusercontent.com/u/5678977?s=40&v=4",
                "username": "tbodt"
            },
            {
                "href": "https://github.com/noah978",
                "avatar": "https://avatars.githubusercontent.com/u/26331126?s=40&v=4",
                "username": "noah978"
            },
            {
                "href": "https://github.com/osy86",
                "avatar": "https://avatars.githubusercontent.com/u/76401173?s=40&v=4",
                "username": "osy86"
            }
        ]
    },
    {
        "author": "iina",
        "name": "iina",
        "avatar": "https://github.com/iina.png",
        "sponsor": "https://github.com/sponsors/iina",
        "url": "https://github.com/iina/iina",
        "description": "The modern video player for macOS.",
        "language": "Swift",
        "languageColor": "#F05138",
        "stars": 41097,
        "fork": 2650,
        "currentPeriodStars": 14,
        "builtBy": [
            {
                "href": "https://github.com/lhc70000",
                "avatar": "https://avatars.githubusercontent.com/u/8478049?s=40&v=4",
                "username": "lhc70000"
            },
            {
                "href": "https://github.com/uiryuu",
                "avatar": "https://avatars.githubusercontent.com/u/20237141?s=40&v=4",
                "username": "uiryuu"
            },
            {
                "href": "https://github.com/low-batt",
                "avatar": "https://avatars.githubusercontent.com/u/86170219?s=40&v=4",
                "username": "low-batt"
            },
            {
                "href": "https://github.com/saagarjha",
                "avatar": "https://avatars.githubusercontent.com/u/13786931?s=40&v=4",
                "username": "saagarjha"
            },
            {
                "href": "https://github.com/svobs",
                "avatar": "https://avatars.githubusercontent.com/u/2213815?s=40&v=4",
                "username": "svobs"
            }
        ]
    },
    {
        "author": "SDWebImage",
        "name": "SDWebImageSwiftUI",
        "avatar": "https://github.com/SDWebImage.png",
        "sponsor": null,
        "url": "https://github.com/SDWebImage/SDWebImageSwiftUI",
        "description": "SwiftUI Image loading and Animation framework powered by SDWebImage",
        "language": "Swift",
        "languageColor": "#F05138",
        "stars": 2436,
        "fork": 248,
        "currentPeriodStars": 1,
        "builtBy": [
            {
                "href": "https://github.com/dreampiggy",
                "avatar": "https://avatars.githubusercontent.com/u/6919743?s=40&v=4",
                "username": "dreampiggy"
            },
            {
                "href": "https://github.com/master-nevi",
                "avatar": "https://avatars.githubusercontent.com/u/987706?s=40&v=4",
                "username": "master-nevi"
            },
            {
                "href": "https://github.com/cci-rmirza",
                "avatar": "https://avatars.githubusercontent.com/u/14853350?s=40&v=4",
                "username": "cci-rmirza"
            },
            {
                "href": "https://github.com/woxtu",
                "avatar": "https://avatars.githubusercontent.com/u/5673994?s=40&v=4",
                "username": "woxtu"
            },
            {
                "href": "https://github.com/cozzin",
                "avatar": "https://avatars.githubusercontent.com/u/11647461?s=40&v=4",
                "username": "cozzin"
            }
        ]
    },
    {
        "author": "AppHouseKitchen",
        "name": "AlDente-Battery_Care_and_Monitoring",
        "avatar": "https://github.com/AppHouseKitchen.png",
        "sponsor": null,
        "url": "https://github.com/AppHouseKitchen/AlDente-Battery_Care_and_Monitoring",
        "description": "Menubar Tool to set Charge Limits and Prolong Battery Lifespan",
        "language": "Swift",
        "languageColor": "#F05138",
        "stars": 8557,
        "fork": 318,
        "currentPeriodStars": 3,
        "builtBy": [
            {
                "href": "https://github.com/MatthiasKerbl",
                "avatar": "https://avatars.githubusercontent.com/u/33470003?s=40&v=4",
                "username": "MatthiasKerbl"
            },
            {
                "href": "https://github.com/davidwernhart",
                "avatar": "https://avatars.githubusercontent.com/u/29832000?s=40&v=4",
                "username": "davidwernhart"
            },
            {
                "href": "https://github.com/pointum",
                "avatar": "https://avatars.githubusercontent.com/u/1675298?s=40&v=4",
                "username": "pointum"
            },
            {
                "href": "https://github.com/cheack",
                "avatar": "https://avatars.githubusercontent.com/u/668493?s=40&v=4",
                "username": "cheack"
            },
            {
                "href": "https://github.com/peterlewis",
                "avatar": "https://avatars.githubusercontent.com/u/820394?s=40&v=4",
                "username": "peterlewis"
            }
        ]
    },
    {
        "author": "mhaeuser",
        "name": "Battery-Toolkit",
        "avatar": "https://github.com/mhaeuser.png",
        "sponsor": null,
        "url": "https://github.com/mhaeuser/Battery-Toolkit",
        "description": "Control the platform power state of your Apple Silicon Mac.",
        "language": "Swift",
        "languageColor": "#F05138",
        "stars": 1474,
        "fork": 41,
        "currentPeriodStars": 9,
        "builtBy": [
            {
                "href": "https://github.com/mhaeuser",
                "avatar": "https://avatars.githubusercontent.com/u/8659494?s=40&v=4",
                "username": "mhaeuser"
            },
            {
                "href": "https://github.com/realrogue",
                "avatar": "https://avatars.githubusercontent.com/u/90951391?s=40&v=4",
                "username": "realrogue"
            },
            {
                "href": "https://github.com/f0xb17",
                "avatar": "https://avatars.githubusercontent.com/u/102655383?s=40&v=4",
                "username": "f0xb17"
            }
        ]
    },
    {
        "author": "quoid",
        "name": "userscripts",
        "avatar": "https://github.com/quoid.png",
        "sponsor": null,
        "url": "https://github.com/quoid/userscripts",
        "description": "An open-source userscript manager for Safari",
        "language": "Swift",
        "languageColor": "#F05138",
        "stars": 3839,
        "fork": 284,
        "currentPeriodStars": 3,
        "builtBy": [
            {
                "href": "https://github.com/quoid",
                "avatar": "https://avatars.githubusercontent.com/u/7660254?s=40&v=4",
                "username": "quoid"
            },
            {
                "href": "https://github.com/ACTCD",
                "avatar": "https://avatars.githubusercontent.com/u/101378590?s=40&v=4",
                "username": "ACTCD"
            },
            {
                "href": "https://github.com/apps/dependabot",
                "avatar": "https://avatars.githubusercontent.com/in/29110?s=40&v=4",
                "username": "apps/dependabot"
            },
            {
                "href": "https://github.com/maggch97",
                "avatar": "https://avatars.githubusercontent.com/u/23057110?s=40&v=4",
                "username": "maggch97"
            },
            {
                "href": "https://github.com/TraderStf",
                "avatar": "https://avatars.githubusercontent.com/u/5954335?s=40&v=4",
                "username": "TraderStf"
            }
        ]
    },
    {
        "author": "groue",
        "name": "GRDB.swift",
        "avatar": "https://github.com/groue.png",
        "sponsor": "https://github.com/sponsors/groue",
        "url": "https://github.com/groue/GRDB.swift",
        "description": "A toolkit for SQLite databases, with a focus on application development",
        "language": "Swift",
        "languageColor": "#F05138",
        "stars": 7647,
        "fork": 768,
        "currentPeriodStars": 4,
        "builtBy": [
            {
                "href": "https://github.com/groue",
                "avatar": "https://avatars.githubusercontent.com/u/54219?s=40&v=4",
                "username": "groue"
            },
            {
                "href": "https://github.com/pakko972",
                "avatar": "https://avatars.githubusercontent.com/u/27460?s=40&v=4",
                "username": "pakko972"
            },
            {
                "href": "https://github.com/swiftlyfalling",
                "avatar": "https://avatars.githubusercontent.com/u/18540905?s=40&v=4",
                "username": "swiftlyfalling"
            },
            {
                "href": "https://github.com/sobri909",
                "avatar": "https://avatars.githubusercontent.com/u/1203835?s=40&v=4",
                "username": "sobri909"
            },
            {
                "href": "https://github.com/mallman",
                "avatar": "https://avatars.githubusercontent.com/u/833693?s=40&v=4",
                "username": "mallman"
            }
        ]
    },
    {
        "author": "ChartsOrg",
        "name": "Charts",
        "avatar": "https://github.com/ChartsOrg.png",
        "sponsor": null,
        "url": "https://github.com/ChartsOrg/Charts",
        "description": "Beautiful charts for iOS/tvOS/OSX! The Apple side of the crossplatform MPAndroidChart.",
        "language": "Swift",
        "languageColor": "#F05138",
        "stars": 27916,
        "fork": 6040,
        "currentPeriodStars": 2,
        "builtBy": [
            {
                "href": "https://github.com/danielgindi",
                "avatar": "https://avatars.githubusercontent.com/u/366926?s=40&v=4",
                "username": "danielgindi"
            },
            {
                "href": "https://github.com/pmairoldi",
                "avatar": "https://avatars.githubusercontent.com/u/296718?s=40&v=4",
                "username": "pmairoldi"
            },
            {
                "href": "https://github.com/liuxuan30",
                "avatar": "https://avatars.githubusercontent.com/u/4375169?s=40&v=4",
                "username": "liuxuan30"
            },
            {
                "href": "https://github.com/jjatie",
                "avatar": "https://avatars.githubusercontent.com/u/19879272?s=40&v=4",
                "username": "jjatie"
            },
            {
                "href": "https://github.com/mathewa6",
                "avatar": "https://avatars.githubusercontent.com/u/5402357?s=40&v=4",
                "username": "mathewa6"
            }
        ]
    },
    {
        "author": "exelban",
        "name": "stats",
        "avatar": "https://github.com/exelban.png",
        "sponsor": "https://github.com/sponsors/exelban",
        "url": "https://github.com/exelban/stats",
        "description": "macOS system monitor in your menu bar",
        "language": "Swift",
        "languageColor": "#F05138",
        "stars": 32557,
        "fork": 1032,
        "currentPeriodStars": 21,
        "builtBy": [
            {
                "href": "https://github.com/exelban",
                "avatar": "https://avatars.githubusercontent.com/u/13332412?s=40&v=4",
                "username": "exelban"
            },
            {
                "href": "https://github.com/jrthsr700tmax",
                "avatar": "https://avatars.githubusercontent.com/u/32911758?s=40&v=4",
                "username": "jrthsr700tmax"
            },
            {
                "href": "https://github.com/Jerry23011",
                "avatar": "https://avatars.githubusercontent.com/u/89069957?s=40&v=4",
                "username": "Jerry23011"
            },
            {
                "href": "https://github.com/Fighter456",
                "avatar": "https://avatars.githubusercontent.com/u/2065714?s=40&v=4",
                "username": "Fighter456"
            },
            {
                "href": "https://github.com/Tai-Zhou",
                "avatar": "https://avatars.githubusercontent.com/u/21986946?s=40&v=4",
                "username": "Tai-Zhou"
            }
        ]
    },
    {
        "author": "vapor",
        "name": "http",
        "avatar": "https://github.com/vapor.png",
        "sponsor": "https://github.com/sponsors/vapor",
        "url": "https://github.com/vapor/http",
        "description": "🚀 Non-blocking, event-driven HTTP built on Swift NIO.",
        "language": "Swift",
        "languageColor": "#F05138",
        "stars": 239,
        "fork": 66,
        "currentPeriodStars": 0,
        "builtBy": [
            {
                "href": "https://github.com/tanner0101",
                "avatar": "https://avatars.githubusercontent.com/u/1342803?s=40&v=4",
                "username": "tanner0101"
            },
            {
                "href": "https://github.com/loganwright",
                "avatar": "https://avatars.githubusercontent.com/u/5750489?s=40&v=4",
                "username": "loganwright"
            },
            {
                "href": "https://github.com/Joannis",
                "avatar": "https://avatars.githubusercontent.com/u/1951674?s=40&v=4",
                "username": "Joannis"
            },
            {
                "href": "https://github.com/shnhrrsn",
                "avatar": "https://avatars.githubusercontent.com/u/42901?s=40&v=4",
                "username": "shnhrrsn"
            },
            {
                "href": "https://github.com/ketzusaka",
                "avatar": "https://avatars.githubusercontent.com/u/1353840?s=40&v=4",
                "username": "ketzusaka"
            }
        ]
    },
    {
        "author": "vapor",
        "name": "core",
        "avatar": "https://github.com/vapor.png",
        "sponsor": "https://github.com/sponsors/vapor",
        "url": "https://github.com/vapor/core",
        "description": "🌎 Utility package containing tools for byte manipulation, Codable, OS APIs, and debugging.",
        "language": "Swift",
        "languageColor": "#F05138",
        "stars": 84,
        "fork": 50,
        "currentPeriodStars": 0,
        "builtBy": [
            {
                "href": "https://github.com/tanner0101",
                "avatar": "https://avatars.githubusercontent.com/u/1342803?s=40&v=4",
                "username": "tanner0101"
            },
            {
                "href": "https://github.com/loganwright",
                "avatar": "https://avatars.githubusercontent.com/u/5750489?s=40&v=4",
                "username": "loganwright"
            },
            {
                "href": "https://github.com/shnhrrsn",
                "avatar": "https://avatars.githubusercontent.com/u/42901?s=40&v=4",
                "username": "shnhrrsn"
            },
            {
                "href": "https://github.com/ketzusaka",
                "avatar": "https://avatars.githubusercontent.com/u/1353840?s=40&v=4",
                "username": "ketzusaka"
            },
            {
                "href": "https://github.com/Joannis",
                "avatar": "https://avatars.githubusercontent.com/u/1951674?s=40&v=4",
                "username": "Joannis"
            }
        ]
    },
    {
        "author": "vapor",
        "name": "vapor",
        "avatar": "https://github.com/vapor.png",
        "sponsor": "https://github.com/sponsors/vapor",
        "url": "https://github.com/vapor/vapor",
        "description": "💧 A server-side Swift HTTP web framework.",
        "language": "Swift",
        "languageColor": "#F05138",
        "stars": 25418,
        "fork": 1493,
        "currentPeriodStars": 0,
        "builtBy": [
            {
                "href": "https://github.com/tanner0101",
                "avatar": "https://avatars.githubusercontent.com/u/1342803?s=40&v=4",
                "username": "tanner0101"
            },
            {
                "href": "https://github.com/loganwright",
                "avatar": "https://avatars.githubusercontent.com/u/5750489?s=40&v=4",
                "username": "loganwright"
            },
            {
                "href": "https://github.com/Joannis",
                "avatar": "https://avatars.githubusercontent.com/u/1951674?s=40&v=4",
                "username": "Joannis"
            },
            {
                "href": "https://github.com/0xTim",
                "avatar": "https://avatars.githubusercontent.com/u/9938337?s=40&v=4",
                "username": "0xTim"
            },
            {
                "href": "https://github.com/gwynne",
                "avatar": "https://avatars.githubusercontent.com/u/1130717?s=40&v=4",
                "username": "gwynne"
            }
        ]
    }
]